rboost/__config.py
rboost/__init__.py
rboost/__main__.py
rboost/rboost.py
rboost/cli/__init__.py
rboost/cli/download.py
rboost/cli/rboost.py
rboost/cli/search.py
rboost/cli/welcome.py
rboost/cli/list/__init__.py
rboost/cli/list/listdocuments.py
rboost/cli/list/listlabels.py
rboost/cli/upload/__init__.py
rboost/cli/upload/uploadpdfs.py
rboost/cli/upload/writenotebook.py
rboost/cli/upload/writeremark.py
rboost/cli/visualize/__init__.py
rboost/cli/visualize/findpath.py
rboost/cli/visualize/loclabel.py
rboost/cli/visualize/printlabel.py
rboost/cli/visualize/showlabels.py
rboost/cli/visualize/shownetwork.py
rboost/config/client_secrets.json
rboost/config/config_install.json
rboost/data/logo.jpg
rboost/data/config/client_secrets.json
rboost/data/config/config_install.json
rboost/data/icons/about.png
rboost/data/icons/code.png
rboost/data/icons/docs.png
rboost/data/icons/documents.png
rboost/data/icons/download.png
rboost/data/icons/home.png
rboost/data/icons/labels.png
rboost/data/icons/loc.png
rboost/data/icons/network.png
rboost/data/icons/notebook.png
rboost/data/icons/path.png
rboost/data/icons/print.png
rboost/data/icons/rboost.png
rboost/data/icons/remark.png
rboost/data/icons/search.png
rboost/data/icons/show.png
rboost/data/icons/upload.png
rboost/data/icons/web.png
rboost/data/icons/write.png
rboost/gui/__init__.py
rboost/gui/__main.py
rboost/gui/home.py
rboost/gui/listdocuments.py
rboost/gui/listlabels.py
rboost/gui/mainwindow.py
rboost/gui/utils/__init__.py
rboost/gui/utils/pandasmodel.py
rboost/source/__init__.py
rboost/source/database.py
rboost/source/gdrive.py
rboost/source/label.py
rboost/source/link.py
rboost/source/network.py
rboost/source/document/__init__.py
rboost/source/document/base.py
rboost/source/document/figure.py
rboost/source/document/notebook.py
rboost/source/document/pdf.py
rboost/source/document/remark.py
rboost/utils/__init__.py
rboost/utils/autocomplete.py
rboost/utils/colormapper.py
rboost/utils/exceptions.py
rboost-0.2.0.dist-info/LICENSE
rboost-0.2.0.dist-info/METADATA
rboost-0.2.0.dist-info/WHEEL
rboost-0.2.0.dist-info/entry_points.txt
rboost-0.2.0.dist-info/top_level.txt
rboost-0.2.0.dist-info/RECORD
