Metadata-Version: 2.1
Name: rboost
Version: 0.2.0
Summary: UNKNOWN
Home-page: https://github.com/SimoneGasperini/rboost.git
Author: SimoneGasperini
Author-email: simone.gasperini2@studio.unibo.it
License: UNKNOWN
Platform: UNKNOWN
Requires-Python: >=3.8
License-File: LICENSE
Requires-Dist: click (==7.1.2)
Requires-Dist: colorama (==0.4.4)
Requires-Dist: gensim (==4.1.2)
Requires-Dist: matplotlib
Requires-Dist: networkx
Requires-Dist: nltk (==3.6.5)
Requires-Dist: pandas
Requires-Dist: pdfminer (==20191125)
Requires-Dist: PyDrive (==1.3.1)
Requires-Dist: pyreadline
Requires-Dist: PySide2
Requires-Dist: pyvis (==0.1.9)
Requires-Dist: setuptools (==58.0.4)
Requires-Dist: tqdm (==4.62.3)
